ChatGPT_PyBot/__init__.py
ChatGPT_PyBot/chatgpt.py
ChatGPT_PyBot-0.4.dist-info/LICENSE
ChatGPT_PyBot-0.4.dist-info/METADATA
ChatGPT_PyBot-0.4.dist-info/WHEEL
ChatGPT_PyBot-0.4.dist-info/entry_points.txt
ChatGPT_PyBot-0.4.dist-info/top_level.txt
ChatGPT_PyBot-0.4.dist-info/RECORD
