Metadata-Version: 2.1
Name: ChatGPT-PyBot
Version: 0.4
Summary: A Python based ChatGPT robot
Home-page: https://github.com/liuhuanshuo/ChatGPT_PyBot
Author: Liuhuanshuo
Author-email: huanshuo080l@gmail.com
License: GNU General Public License v2.0
Classifier: Programming Language :: Python :: 3
Classifier: Operating System :: OS Independent
Requires-Python: >=3.7
License-File: LICENSE
Requires-Dist: rich
Requires-Dist: requests
Requires-Dist: OpenAIAuth
